git2prompt/__init__.py
git2prompt/__main__.py
git2prompt-0.1.0.dist-info/LICENSE
git2prompt-0.1.0.dist-info/METADATA
git2prompt-0.1.0.dist-info/WHEEL
git2prompt-0.1.0.dist-info/entry_points.txt
git2prompt-0.1.0.dist-info/RECORD
