Metadata-Version: 2.1
Name: git2prompt
Version: 0.1.0
Summary: Tool for converting the contents of a git repository to a single markdown file that can be used in an LLM prompt.
License: MIT
Author: Sean Fitzgerald
Author-email: sean@fitzgeralds.me
Requires-Python: >=3.11,<4.0
Classifier: License :: OSI Approved :: MIT License
Classifier: Programming Language :: Python :: 3
Classifier: Programming Language :: Python :: 3.11
Classifier: Programming Language :: Python :: 3.12
Requires-Dist: igittigitt (>=2.1.4,<3.0.0)
